parseweb/__init__.py
parseweb/parseweb_file.py
parseweb-3.dist-info/METADATA
parseweb-3.dist-info/WHEEL
parseweb-3.dist-info/top_level.txt
parseweb-3.dist-info/RECORD
